{
  "id": "6eme_PHIL_CH1_P2_QUIZ13",
  "classe": "6eme",
  "matiere": "Philosophie",
  "chapitre": "chapitre_1",
  "partie": "partie_2",
  "titre": "Obéissance et Choix",
  "questions": [
    {
      "id": "q1",
      "question": "Pourquoi obéit-on à des règles (à l'école, à la maison) ?",
      "type": "QCM",
      "options": ["Pour faire plaisir aux chefs", "Parce que les règles permettent de vivre ensemble en sécurité", "Parce qu'on n'a pas le choix", "Pour gagner des cadeaux"],
      "bonne_reponse": "Parce que les règles permettent de vivre ensemble en sécurité",
      "explication": "La règle est une 'limite positive' qui protège chacun."
    },
    {
      "id": "q2",
      "question": "Une 'bonne' obéissance est une obéissance :",
      "type": "QCM",
      "options": ["Aveugle (sans réfléchir)", "Réfléchie (on comprend pourquoi la règle existe)", "Forcée par la peur", "Uniquement quand on nous regarde"],
      "bonne_reponse": "Réfléchie (on comprend pourquoi la règle existe)",
      "explication": "C'est l'essence de la citoyenneté."
    },
    {
      "id": "q3",
      "question": "Vrai ou Faux : Être libre, c'est aussi assumer les conséquences de ses choix.",
      "type": "Vrai/Faux",
      "options": ["Vrai", "Faux"],
      "bonne_reponse": "Vrai",
      "explication": "La liberté va de pair avec la responsabilité."
    },
    {
      "id": "q4",
      "question": "Si une règle te semble très injuste, que dit la philosophie ?",
      "type": "QCM",
      "options": ["Il faut obéir sans rien dire", "Il faut en discuter, essayer de comprendre ou proposer de l'améliorer", "Il faut tout casser", "Il faut s'enfuir"],
      "bonne_reponse": "Il faut en discuter, essayer de comprendre ou proposer de l'améliorer",
      "explication": "C'est l'usage de la raison pour faire évoluer le monde."
    },
    {
      "id": "q5",
      "question": "Choisir, c'est souvent 'renoncer'. Pourquoi ?",
      "type": "QCM",
      "options": ["Parce qu'on ne peut pas tout avoir en même temps", "Parce que choisir rend triste", "Parce que c'est interdit", "On ne renonce jamais"],
      "bonne_reponse": "Parce qu'on ne peut pas tout avoir en même temps",
      "explication": "Choisir un chemin, c'est s'engager dans une direction."
    }
  ]
}
