{
  "id": "quiz18",
  "titre": "Insolite et Divers (1)",
  "questions": [
    {
      "id": "q1",
      "type": "qcm",
      "enonce": "Quel pays a pour surnom 'Le pays du soleil levant' ?",
      "options": [
        "Le Japon",
        "La Chine",
        "La Corée",
        "Le Vietnam"
      ],
      "correctIndex": 0
    },
    {
      "id": "q2",
      "type": "vrai_faux",
      "enonce": "On ne peut pas voir la Grande Muraille de Chine depuis la Lune à l'oeil nu.",
      "reponse": true
    },
    {
      "id": "q3",
      "type": "trous",
      "enonce": "Le nom du navire insubmersible qui a coulé en 1912 est le {{1}} (Titanic).",
      "reponsesAttendues": [
        "Titanic"
      ]
    },
    {
      "id": "q4",
      "type": "qcm",
      "enonce": "Quel est l'aliment de base de la moitié de la population mondiale ?",
      "options": [
        "Le riz",
        "Le blé",
        "Le maïs",
        "La pomme de terre"
      ],
      "correctIndex": 0
    },
    {
      "id": "q5",
      "type": "vrai_faux",
      "enonce": "Le miel est le seul aliment qui ne se périme jamais.",
      "reponse": true
    },
    {
      "id": "q6",
      "type": "qcm",
      "enonce": "Lalquel de ces fruits contient le plus de vitamine C ?",
      "options": [
        "Le kiwi",
        "L'orange",
        "La pomme",
        "La banane"
      ],
      "correctIndex": 0
    },
    {
      "id": "q7",
      "type": "trous",
      "enonce": "L'empereur français célèbre pour sa petite taille (en réalité moyenne) et ses conquêtes est {{1}} Ier (Napoléon).",
      "reponsesAttendues": [
        "Napoléon"
      ]
    },
    {
      "id": "q8",
      "type": "vrai_faux",
      "enonce": "Une tomate est scientifiquement un légume.",
      "reponse": false
    },
    {
      "id": "q9",
      "type": "qcm",
      "enonce": "Quelle couleur obtient-on en mélangeant du bleu et du jaune ?",
      "options": [
        "Vert",
        "Violet",
        "Orange",
        "Marron"
      ],
      "correctIndex": 0
    },
    {
      "id": "q10",
      "type": "vrai_faux",
      "enonce": " 'L'habit ne fait pas le moine' signifie qu'il ne faut pas se fier aux apparences.",
      "reponse": true
    }
  ]
}
