{"id":"quiz5","titre":"Addition de fractions (Même dénominateur)","questions":[{"id":"q1","type":"qcm","enonce":"Pour additionner deux fractions de même dénominateur, que fait-on ?","options":["On additionne les numérateurs et les dénominateurs","On additionne uniquement les numérateurs et on garde le dénominateur","On multiplie tout","On fait un produit en croix"],"correctIndex":1},{"id":"q2","type":"vrai_faux","enonce":"2/7 + 3/7 = 5/14.","reponse":false},{"id":"q3","type":"trous","enonce":"Calcule 1/9 + 4/9. Le résultat est {{1}}/9.","reponsesAttendues":["5"]},{"id":"q4","type":"relier","question":"Associe le calcul au résultat.","pairs":[{"left":"10/3 - 2/3","right":"8/3"},{"left":"1/4 + 2/4","right":"3/4"},{"left":"5/10 + 5/10","right":"1"}]},{"id":"q5","type":"qcm","enonce":"Calcule 7/12 + 5/12 :","options":["12/24","1","2/12","35/144"],"correctIndex":1}]}