{
  "id": "2-snt-ch1-q10",
  "titre": "Récapitulatif Web",
  "questions": [
    {
      "type": "qcm",
      "question": "Lequel de ces langages est indispensable pour créer le CONTENU d'une page ?",
      "options": ["Python", "HTML", "C++", "Java"],
      "answer": "HTML"
    },
    {
      "type": "vrai_faux",
      "question": "Le navigateur Web interprète le code reçu du serveur pour l'afficher à l'écran.",
      "answer": true
    },
    {
      "type": "qcm",
      "question": "Que signifie le S dans HTTPS ?",
      "options": ["Simple", "Secure (Sécurisé)", "Secret", "Site"],
      "answer": "Secure (Sécurisé)"
    },
    {
      "type": "vrai_faux",
      "question": "Le Web est mondial et décentralisé.",
      "answer": true
    },
    {
      "type": "qcm",
      "question": "Quel composant fait la liaison entre votre nom et l'adresse physique du serveur ?",
      "options": ["Le clavier", "Le DNS", "La souris", "La batterie"],
      "answer": "Le DNS"
    }
  ]
}
