{
  "id": "quiz9",
  "titre": "Le Temps",
  "questions": [
    {
      "id": "q1",
      "type": "qcm",
      "enonce": "Que signifie 'Dies' ?",
      "options": [
        "Le jour",
        "La nuit",
        "L'heure",
        "L'année"
      ],
      "correctIndex": 0
    },
    {
      "id": "q2",
      "type": "vrai_faux",
      "enonce": "'Nox' signifie le matin.",
      "reponse": false
    },
    {
      "id": "q3",
      "type": "trous",
      "enonce": "L'année se dit {{1}} en latin.",
      "reponsesAttendues": [
        "Annus"
      ]
    },
    {
      "id": "q4",
      "type": "relier",
      "pairs": [
        {
          "left": "Mensis",
          "right": "Mois"
        },
        {
          "left": "Hora",
          "right": "Heure"
        },
        {
          "left": "Tempus",
          "right": "Temps"
        }
      ]
    },
    {
      "id": "q5",
      "type": "qcm",
      "enonce": "Comment dit-on 'Aujourd'hui' ?",
      "options": [
        "Heri",
        "Hodie",
        "Cras",
        "Nunc"
      ],
      "correctIndex": 1
    }
  ]
}
