{
  "id": "quiz82",
  "titre": "JavaScript Expert : Classes Modernes (ES2022+)",
  "questions": [
    {
      "id": "q1",
      "type": "qcm",
      "enonce": "Quel préfixe permet de déclarer une propriété ou une méthode privée dans une classe JS ?",
      "options": [
        "# (hashtag)",
        "_",
        "private",
        "!"
      ],
      "correctIndex": 0
    },
    {
      "id": "q2",
      "type": "vrai_faux",
      "enonce": "Les membres privés (avec #) sont accessibles depuis l'extérieur de la classe via l'indexation par chaîne (ex: `obj['#prop']`).",
      "reponse": false
    },
    {
      "id": "q3",
      "type": "trous",
      "enonce": "Les `{{1}}` (Static Blocks) introduits en ES2022 permettent d'exécuter du code d'initialisation complexe pour les membres statiques d'une classe.",
      "reponsesAttendues": [
        "blocs statiques",
        "static blocks"
      ]
    },
    {
      "id": "q4",
      "type": "qcm",
      "enonce": "Comment vérifie-t-on si un objet possède un membre privé #prop sans provoquer d'erreur s'il est absent ?",
      "options": [
        "if (#prop in obj)",
        "if (obj.has(#prop))",
        "if (typeof obj.#prop !== 'undefined')",
        "C'est impossible"
      ],
      "correctIndex": 0
    },
    {
      "id": "q5",
      "type": "vrai_faux",
      "enonce": "On peut déclarer des méthodes statiques privées (ex: `static #myMethod`).",
      "reponse": true
    },
    {
      "id": "q6",
      "type": "qcm",
      "enonce": "Quel mot-clé permet d'accéder aux membres de la classe parente dans une sous-classe ?",
      "options": [
        "super",
        "parent",
        "this.base",
        "prototype"
      ],
      "correctIndex": 0
    },
    {
      "id": "q7",
      "type": "trous",
      "enonce": "Les `{{1}}` (Public Class Fields) permettent de déclarer des propriétés directement dans le corps de la classe sans passer par le constructeur.",
      "reponsesAttendues": [
        "champs publics",
        "public class fields"
      ]
    },
    {
      "id": "q8",
      "type": "vrai_faux",
      "enonce": "L'encapsulation via les champs privés est une encapsulation 'hard' (réellement protégée par le moteur JS).",
      "reponse": true
    },
    {
      "id": "q9",
      "type": "qcm",
      "enonce": "Que se passe-t-il si vous essayez de déclarer un membre privé commençant par un chiffre after le # ?",
      "options": [
        "Erreur de syntaxe",
        "C'est autorisé",
        "Il est considéré comme public",
        "Il est ignoré"
      ],
      "correctIndex": 0
    },
    {
      "id": "q10",
      "type": "vrai_faux",
      "enonce": "Les membres privés ne peuvent pas être renommés via la déstructuration.",
      "reponse": true
    }
  ]
}
