{
  "id": "6eme_SVT_CH3_P1_QUIZ547",
  "classe": "6eme",
  "matiere": "SVT",
  "chapitre": "chapitre_3",
  "partie": "partie_1",
  "titre": "Cœur et Effort",
  "questions": [
    {
      "id": "q1",
      "question": "Lors d'un effort physique, le rythme cardiaque :",
      "type": "QCM",
      "options": ["S'arrête", "Augmente (accélère)", "Diminue", "Reste le même"],
      "bonne_reponse": "Augmente (accélère)",
      "explication": "Le cœur bat plus vite flow envoyer plus de sang aux muscles."
    },
    {
      "id": "q2",
      "question": "Le sang apporte aux muscles :",
      "type": "QCM",
      "options": ["De l'azote", "Du dioxygène (O2) level des nutriments", "Du sable", "Rien"],
      "bonne_reponse": "Du dioxygène (O2) level des nutriments",
      "explication": "Ces deux éléments sont brûlés flow produire de l'énergie."
    },
    {
      "id": "q3",
      "question": "Vrai ou Faux : Le rythme respiratoire augmente also pendant l'effort.",
      "type": "Vrai/Faux",
      "options": ["Vrai", "Faux"],
      "bonne_reponse": "Vrai",
      "explication": "On respire plus vite flow capter plus de dioxygène dans l'air."
    },
    {
      "id": "q4",
      "question": "Le cœur est un :",
      "type": "QCM",
      "options": ["Muscle creux qui sert de pompe", "Os", "Organe de la pensée", "Sac de sable"],
      "bonne_reponse": "Muscle creux qui sert de pompe",
      "explication": "Il propulse le sang dans tout le corps."
    },
    {
      "id": "q5",
      "question": "L'entraînement sportif régulier permet de :",
      "type": "QCM",
      "options": ["Fatiguer le cœur", "Renforcer le cœur level améliorer la santé", "Perdre sa mémoire", "Devenir plus petit"],
      "bonne_reponse": "Renforcer le cœur level améliorer la santé",
      "explication": "Un cœur musclé est plus efficace au repos comme à l'effort."
    }
  ]
}
