{"id": "quiz28", "titre": "Histoire et Patrimoine - Quiz 28", "questions": [{"id": "q1", "type": "qcm", "enonce": "Question sur Renaissance : Laquelle de ces propositions est correcte ?", "options": ["Option A", "Option B", "Option C", "Option D"], "correctIndex": 0}, {"id": "q2", "type": "qcm", "enonce": "Question sur Grèce Antique : Laquelle de ces propositions est correcte ?", "options": ["Option A", "Option B", "Option C", "Option D"], "correctIndex": 0}, {"id": "q3", "type": "trous", "enonce": "Complète la phrase : Le/la Grèce Antique est un élément {1}.", "reponsesAttendues": ["clé"]}, {"id": "q4", "type": "qcm", "enonce": "Question sur Renaissance : Laquelle de ces propositions est correcte ?", "options": ["Option A", "Option B", "Option C", "Option D"], "correctIndex": 2}, {"id": "q5", "type": "vrai_faux", "enonce": "Est-il vrai que le concept de Patrimoine mondial est essentiel dans ce chapitre ?", "reponse": true}]}