{
  "id": "6eme_SES_CH1_P2_QUIZ17",
  "classe": "6eme",
  "matiere": "SES",
  "chapitre": "chapitre_1",
  "partie": "partie_2",
  "titre": "L'Entreprise Responsable",
  "questions": [
    {
      "id": "q1",
      "question": "Qu'est-ce que la Responsabilité Sociétale des Entreprises (RSE) ?",
      "type": "QCM",
      "options": ["Le fait de ne pas payer d'impôts", "Le fait pour l'entreprise de faire attention à l'environnement et à ses salariés", "Un moyen pour le patron de partir en vacances", "Le logo sur le bâtiment"],
      "bonne_reponse": "Le fait pour l'entreprise de faire attention à l'environnement et à ses salariés",
      "explication": "L'entreprise cherche à être bénéfique pour la société."
    },
    {
      "id": "q2",
      "question": "Un geste écolo d'une entreprise est :",
      "type": "QCM",
      "options": ["Réduire ses déchets et recycler", "Utiliser le plus de plastique possible", "Laisser les lumières allumées la nuit", "Ne rien faire"],
      "bonne_reponse": "Réduire ses déchets et recycler",
      "explication": "C'est une action concrète de RSE."
    },
    {
      "id": "q3",
      "question": "Vrai ou Faux : Traiter ses employés avec respect fait partie de la RSE.",
      "type": "Vrai/Faux",
      "options": ["Vrai", "Faux"],
      "bonne_reponse": "Vrai",
      "explication": "Le bien-être des travailleurs est socialement responsable."
    },
    {
      "id": "q4",
      "question": "Une entreprise qui achète ses produits localement aide :",
      "type": "QCM",
      "options": ["Uniquement elle-même", "L'économie de sa région et limite la pollution du transport", "À rien du tout", "À dépenser plus d'argent pour rien"],
      "bonne_reponse": "L'économie de sa région et limite la pollution du transport",
      "explication": "C'est l'approvisionnement local."
    },
    {
      "id": "q5",
      "question": "La RSE est importante car :",
      "type": "QCM",
      "options": ["Elle donne une mauvaise image", "Elle aide à préserver le futur de tous", "Elle est interdite par la loi", "Elle fait baisser la production"],
      "bonne_reponse": "Elle aide à préserver le futur de tous",
      "explication": "C'est l'économie au service du vivant."
    }
  ]
}
