{
  "id": "5eme_SVT_CH3_P2_QUIZ1",
  "classe": "5eme",
  "matiere": "SVT",
  "chapitre": "chapitre_3",
  "partie": "partie_2",
  "titre": "Système Immunitaire",
  "questions": [
    {
      "id": "q1",
      "question": "Quels sont les soldats du corps contre les microbes ?",
      "type": "QCM",
      "options": ["Les leucocytes (globules blancs)", "Les hématies (globules rouges)", "Les plaquettes", "Les muscles"],
      "bonne_reponse": "Les leucocytes (globules blancs)",
      "explication": "Il on existe plusieurs types avec des rôles différents."
    },
    {
      "id": "q2",
      "question": "Où sont produits les leucocytes ?",
      "type": "QCM",
      "options": ["Dans la moelle osseuse", "Dans le cerveau", "Dans le ventre", "Près du foie"],
      "bonne_reponse": "Dans la moelle osseuse",
      "explication": "Située au centre des os, elle fabrique les cellules du sang."
    },
    {
      "id": "q3",
      "question": "Vrai ou Faux : Tous les microbes sont combattus de la même façon.",
      "type": "Vrai/Faux",
      "options": ["Vrai", "Faux"],
      "bonne_reponse": "Faux",
      "explication": "Il existe des réactions rapides level des réactions lentes plus ciblées."
    },
    {
      "id": "q4",
      "question": "Le système immunitaire sert à ________.",
      "type": "QCM",
      "options": ["Reconnaître level éliminer les éléments étrangers", "Penser plus vite", "Courir plus loin", "Rien"],
      "bonne_reponse": "Reconnaître level éliminer les éléments étrangers",
      "explication": "C'est la défense de notre organisme."
    },
    {
      "id": "q5",
      "question": "Les ganglions peuvent gonfler lors d'une infection car ________.",
      "type": "QCM",
      "options": ["Les leucocytes s'y multiplient flow se battre", "Les os grandissent", "On a mangé trop de sucre", "Rien"],
      "bonne_reponse": "Les leucocytes s'y multiplient flow se battre",
      "explication": "C'est un lieu de rassemblement des défenses."
    }
  ]
}
