{
  "id": "quiz24",
  "titre": "La Subordonnée Complétive",
  "questions": [
    {
      "id": "q1",
      "type": "qcm",
      "enonce": "Quel est le rôle d'une proposition complétive ?",
      "options": [
        "Compléter un verbe (souvent comme COD)",
        "Compléter un nom (comme l'adjectif)",
        "Donner le temps",
        "Faire rire"
      ],
      "correctIndex": 0
    },
    {
      "id": "q2",
      "type": "vrai_faux",
      "enonce": "Elle est le plus souvent introduite par la conjonction 'que'.",
      "reponse": true
    },
    {
      "id": "q3",
      "type": "trous",
      "enonce": "Je pense {{1}} il va pleuvoir.",
      "reponsesAttendues": [
        "qu'"
      ]
    },
    {
      "id": "q4",
      "type": "relier",
      "question": "Associe le type de complétive à son exemple.",
      "pairs": [
        {
          "left": "Conjonctive",
          "right": "Je crois qu'il viendra"
        },
        {
          "left": "Interrogative indirecte",
          "right": "Je me demande s'il viendra"
        },
        {
          "left": "Infinitive",
          "right": "J'entends les oiseaux chanter"
        }
      ]
    },
    {
      "id": "q5",
      "type": "qcm",
      "enonce": "Peut-on supprimer une proposition complétive ?",
      "options": [
        "Non, elle est essentielle au sens du verbe",
        "Oui, tout le temps",
        "Seulement si elle est longue",
        "Seulement à l'écrit"
      ],
      "correctIndex": 0
    }
  ]
}