{
  "id": "6eme_PC_CH1_P1_QUIZ10",
  "classe": "6eme",
  "matiere": "Physique-Chimie",
  "chapitre": "chapitre_1",
  "partie": "partie_1",
  "titre": "Défi PC : La matière",
  "questions": [
    {
      "id": "q1",
      "question": "Quelle propriété définit un gaz ?",
      "type": "QCM",
      "options": ["Expansible et compressible", "Dur et incassable", "Plane et horizontale", "Invisible et solide"],
      "bonne_reponse": "Expansible et compressible",
      "explication": "Le gaz occupe tout l'espace et on peut réduire son volume."
    },
    {
      "id": "q2",
      "question": "Le passage de solide à liquide s'appelle :",
      "type": "QCM",
      "options": ["Solidification", "Fusion", "Liquéfaction", "Vaporisation"],
      "bonne_reponse": "Fusion",
      "explication": "Comme un glaçon qui fond."
    },
    {
      "id": "q3",
      "question": "Vrai ou Faux : 1 litre d'eau pèse 1 kg.",
      "type": "Vrai/Faux",
      "options": ["Vrai", "Faux"],
      "bonne_reponse": "Vrai",
      "explication": "Correct pour l'eau pure."
    },
    {
      "id": "q4",
      "question": "Quel instrument mesure le volume d'un liquide ?",
      "type": "QCM",
      "options": ["Balance", "Thermomètre", "Éprouvette graduée", "Règle"],
      "bonne_reponse": "Éprouvette graduée",
      "explication": "Elle permet de lire le niveau du liquide."
    },
    {
      "id": "q5",
      "question": "Qu'est-ce qu'une particule ?",
      "type": "QCM",
      "options": ["Un gros caillou", "Un élément minuscule de matière", "Un instrument de musique", "Un type de nuage"],
      "bonne_reponse": "Un élément minuscule de matière",
      "explication": "Atomes et molécules sont les particules de base."
    }
  ]
}
