{"id":"quiz9","titre":"Clima y naturaleza","questions":[{"id":"q1","type":"qcm","enonce":"¿Cuál es la selva más grande del mundo (en América del Sur)?","options":["La selva del Congo","El Amazonas","La selva de Borneo"],"correctIndex":1},{"id":"q2","type":"vrai_faux","enonce":"Los Andes es la cordillera más larga de América del Sur.","reponse":true},{"id":"q3","type":"qcm","enonce":"¿Cómo es el clima en el desierto de Atacama?","options":["Muy húmedo","Extremadamente seco","Nevado"],"correctIndex":1},{"id":"q4","type":"trous","enonce":"España está en el sur de {{1}}.","reponsesAttendues":["Europa"]},{"id":"q5","type":"vrai_faux","enonce":"El español es una lengua romance (derivada del latín).","reponse":true}]}
