{"id":"quiz3","titre":"Guy de Maupassant","questions":[{"id":"q1","type":"qcm","enonce":"Quel est le titre de la nouvelle où un être invisible hante le narrateur ?","options":["La Parure","Le Horla","Bel-Ami","Une Vie"],"correctIndex":1},{"id":"q2","type":"vrai_faux","enonce":"Maupassant était un disciple de Flaubert.","reponse":true},{"id":"q3","type":"trous","enonce":"Dans 'La Parure', Mathilde Loisel perd un collier de {{1}}.","reponsesAttendues":["diamants"]},{"id":"q4","type":"relier","question":"Associe la nouvelle à sa chute.","pairs":[{"left":"La Parure","right":"Le collier était faux"},{"left":"Le Horla","right":"Le narrateur sombre dans la folie"},{"left":"Boule de Suif","right":"Hypocrisie de la bourgeoisie"}]},{"id":"q5","type":"qcm","enonce":"Maupassant écrit principalement des :","options":["Poèmes","Pièces de théâtre","Nouvelles et romans","Essais"],"correctIndex":2}]}