{"id":"quiz10","titre":"Final 3rd Grade Review","questions":[{"id":"q1","type":"qcm","enonce":"Which sentence is correct?","options":["He has go to London yesterday","He went to London yesterday","He is go to London yesterday","He gone to London yesterday"],"correctIndex":1},{"id":"q2","type":"vrai_faux","enonce":"English is the official language of the USA.","reponse":true},{"id":"q3","type":"trous","enonce":"The plural of 'child' is {{1}}.","reponsesAttendues":["children"]},{"id":"q4","type":"relier","question":"Match the question to the answer.","pairs":[{"left":"How old are you?","right":"I'm 14"},{"left":"Where are you from?","right":"I'm from France"},{"left":"How are you?","right":"I'm fine, thanks"}]},{"id":"q5","type":"qcm","enonce":"Good luck for your exams! You ... work hard.","options":["must","shouldn't","can't","might"],"correctIndex":0}]}