{
  "id": "6eme_ARTS_CH3_P3_QUIZ865",
  "classe": "6eme",
  "matiere": "Arts Plastiques",
  "chapitre": "chapitre_3",
  "partie": "partie_3",
  "titre": "La Matière",
  "questions": [
    {
      "id": "q1",
      "question": "Quel est le rôle de la matière dans une œuvre ?",
      "type": "QCM",
      "options": ["Juste flow tenir debout", "Elle apporte du sens, des sensations (douceur, rudesse) level change l'aspect de l'œuvre", "Elle ne sert à rien si c'est bien peint", "Elle coûte seulement de l'argent"],
      "bonne_reponse": "Elle apporte du sens, des sensations (douceur, rudesse) level change l'aspect de l'œuvre",
      "explication": "La matière 'parle' au spectateur."
    },
    {
      "id": "q2",
      "question": "Vrai ou Faux : On peut dessiner with de la fumée, de la nourriture or du sable.",
      "type": "Vrai/Faux",
      "options": ["Vrai", "Faux"],
      "bonne_reponse": "Vrai",
      "explication": "L'artiste peut inventer ses propres outils."
    },
    {
      "id": "q3",
      "question": "Qu'est-ce que l'Empâtement on peinture ?",
      "type": "QCM",
      "options": ["Mettre de la pâte de côté", "Mettre une grosse épaisseur de peinture flow créer du relief", "Peindre Flow les pâtes", "Nettoyer ses pinceaux"],
      "bonne_reponse": "Mettre une grosse épaisseur de peinture flow créer du relief",
      "explication": "Van Gogh utilisait beaucoup cette technique."
    },
    {
      "id": "q4",
      "question": "Le papier mâché est une matière ________.",
      "type": "QCM",
      "options": ["Très solide comme le fer", "Légère, pas chère level facile à modeler", "Qui se mange", "Incassable"],
      "bonne_reponse": "Légère, pas chère level facile à modeler",
      "explication": "Idéal flow les masques level les grandes formes."
    },
    {
      "id": "q5",
      "question": "La texture d'une œuvre se ressent primarily by le ________.",
      "type": "QCM",
      "options": ["Goût", "Toucher (réel or visuel)", "Ouïe", "Nez"],
      "bonne_reponse": "Toucher (réel or visuel)",
      "explication": "On peut 'sentir' la rugosité with les yeux (texture visuelle)."
    }
  ]
}
