{
  "id": "quiz27",
  "titre": "Les Mythes Célèbres",
  "questions": [
    {
      "id": "q1",
      "type": "qcm",
      "enonce": "Quel héros grec a combattu le Minotaure dans le labyrinthe ?",
      "options": [
        "Hercule",
        "Thésée",
        "Ulysse",
        "Achille"
      ],
      "correctIndex": 1
    },
    {
      "id": "q2",
      "type": "vrai_faux",
      "enonce": "Icare s'est brûlé les ailes en volant trop près du soleil.",
      "reponse": true
    },
    {
      "id": "q3",
      "type": "trous",
      "enonce": "Le monstre à corps d'homme et tête de taureau s'appelle le {{1}}.",
      "reponsesAttendues": [
        "Minotaure"
      ]
    },
    {
      "id": "q4",
      "type": "qcm",
      "enonce": "Quel était le point faible d'Achille ?",
      "options": [
        "Son nez",
        "Sa main",
        "Son talon",
        "Son dos"
      ],
      "correctIndex": 2
    },
    {
      "id": "q5",
      "type": "vrai_faux",
      "enonce": "Pandore a ouvert une boîte qui a libéré tous les maux de l'humanité.",
      "reponse": true
    },
    {
      "id": "q6",
      "type": "qcm",
      "enonce": "Qui est le chien à trois têtes qui garde les enfers ?",
      "options": [
        "Médor",
        "Cerbère",
        "Pluton",
        "Arès"
      ],
      "correctIndex": 1
    },
    {
      "id": "q7",
      "type": "trous",
      "enonce": "Le voyage d'Ulysse pour rentrer chez lui s'appelle l'{{1}}.",
      "reponsesAttendues": [
        "Odyssée"
      ]
    },
    {
      "id": "q8",
      "type": "vrai_faux",
      "enonce": "Le cheval de Troie était rempli de soldats grecs.",
      "reponse": true
    },
    {
      "id": "q9",
      "type": "qcm",
      "enonce": "Quel dieu a offert le feu aux hommes (et a été puni par Zeus) ?",
      "options": [
        "Prométhée",
        "Atlas",
        "Bacchus",
        "Hermès"
      ],
      "correctIndex": 0
    },
    {
      "id": "q10",
      "type": "vrai_faux",
      "enonce": "Les mythes servaient à expliquer le monde aux anciens.",
      "reponse": true
    }
  ]
}
