{
  "id": "quiz7",
  "titre": "La biomasse",
  "questions": [
    {
      "id": "q1",
      "type": "qcm",
      "enonce": "Qu'est-ce que la biomasse ?",
      "options": [
        "Une masse d'eau",
        "L'ensemble des matières organiques (bois, déchets agricoles, plantes)",
        "De la boue",
        "L'énergie des aimants"
      ],
      "correctIndex": 1
    },
    {
      "id": "q2",
      "type": "vrai_faux",
      "enonce": "Le bois est la première source d'énergie biomasse utilisée pour le chauffage.",
      "reponse": true
    },
    {
      "id": "q3",
      "type": "trous",
      "enonce": "On peut transformer les plantes en carburant appelé {{1}}.",
      "reponsesAttendues": [
        "biocarburant"
      ]
    },
    {
      "id": "q4",
      "type": "relier",
      "question": "Associe l'usage de la biomasse.",
      "pairs": [
        {
          "left": "Bûches",
          "right": "Chauffage domestique"
        },
        {
          "left": "Méthanisation",
          "right": "Production de gaz à partir de déchets"
        },
        {
          "left": "Bioéthanol",
          "right": "Transport (essence végétale)"
        }
      ]
    },
    {
      "id": "q5",
      "type": "qcm",
      "enonce": "Pourquoi la biomasse est-elle renouvelable ?",
      "options": [
        "Parce qu'on peut replanter les végétaux en quelques années",
        "Parce qu'elle ne brûle pas",
        "Parce qu'elle est verte",
        "Parce qu'elle n'a pas de fin"
      ],
      "correctIndex": 0
    }
  ]
}
