{"id":"quiz6","titre":"L'Encyclopédie","questions":[{"id":"q1","type":"qcm","enonce":"Quels sont les deux principaux directeurs de l'Encyclopédie ?","options":["Voltaire et Rousseau","Diderot et d'Alembert","Montesquieu et Marivaux","Molière et Racine"],"correctIndex":1},{"id":"q2","type":"vrai_faux","enonce":"L'Encyclopédie avait pour but de rassembler toutes les connaissances humaines et de les diffuser pour éclairer les esprits.","reponse":true},{"id":"q3","type":"trous","enonce":"L'Encyclopédie a été publiée entre 1751 et {{1}} (année).","reponsesAttendues":["1772"]},{"id":"q4","type":"relier","question":"Associe.","pairs":[{"left":"Diderot","right":"Philosophe et écrivain, maître d'œuvre de l'ouvrage"},{"left":"D'Alembert","right":"Mathématicien, auteur du Discours préliminaire"},{"left":"Planches","right":"Illustrations techniques et artistiques"}]},{"id":"q5","type":"qcm","enonce":"L'Encyclopédie a-t-elle subi la censure ?","options":["Non, jamais","Oui, elle a même été interdite à plusieurs reprises","Seulement pour les parties mathématiques","Uniquement après la Révolution"],"correctIndex":1}]}