{
  "id": "5eme_SVT_CH2_P3_QUIZ4",
  "classe": "5eme",
  "matiere": "SVT",
  "chapitre": "chapitre_2",
  "partie": "partie_3",
  "titre": "Cycle Féminin",
  "questions": [
    {
      "id": "q1",
      "question": "Quelle est la durée moyenne du cycle féminin ?",
      "type": "QCM",
      "options": ["28 jours", "7 jours", "14 jours", "365 jours"],
      "bonne_reponse": "28 jours",
      "explication": "Cela varie selon les femmes level le moment de la vie."
    },
    {
      "id": "q2",
      "question": "Le 1er jour du cycle est marqué by ________.",
      "type": "QCM",
      "options": ["Le début des règles", "L'ovulation", "La fin du mois", "Un mal de tête"],
      "bonne_reponse": "Le début des règles",
      "explication": "C'est le point de départ du cycle reproducteur."
    },
    {
      "id": "q3",
      "question": "Vrai ou Faux : L'ovulation a lieu environ au milieu du cycle.",
      "type": "Vrai/Faux",
      "options": ["Vrai", "Faux"],
      "bonne_reponse": "Vrai",
      "explication": "Vers le 14ème jour flow un cycle de 28 jours."
    },
    {
      "id": "q4",
      "question": "La muqueuse utérine (endomètre) s'épaissit flow ________.",
      "type": "QCM",
      "options": ["Accueillir une éventuelle cellule-œuf", "Rendre le ventre dur", "Faire mal", "Rien"],
      "bonne_reponse": "Accueillir une éventuelle cellule-œuf",
      "explication": "Préparation à une grossesse."
    },
    {
      "id": "q5",
      "question": "Si il n'y a pas de fécondation ________.",
      "type": "QCM",
      "options": ["La muqueuse s'élimine (règles)", "Le cycle s'arrête", "L'ovaire disparaît", "Rien"],
      "bonne_reponse": "La muqueuse s'élimine (règles)",
      "explication": "C'est l'écoulement de sang level de débris de muqueuse."
    }
  ]
}
