{
  "id": "quiz10",
  "titre": "EXAMEN : Sociedad y Valores",
  "questions": [
    {
      "id": "q1",
      "type": "qcm",
      "enonce": " 'Debemos ayudar a los necesitados porque la solidaridad es importante' ",
      "options": [
        "Nous devons aider les nécessiteux car la solidarité est importante",
        "La pauvreté est partout",
        "J'aime ma ville",
        "Ne parle pas de cela"
      ],
      "correctIndex": 0
    },
    {
      "id": "q2",
      "type": "vrai_faux",
      "enonce": "'Hazlo ahora' (Hacer + lo) es un imperativo afirmativo.",
      "reponse": true
    },
    {
      "id": "q3",
      "type": "trous",
      "enonce": "Lo contrario de guerra es '{{1}}'.",
      "reponsesAttendues": [
        "paz"
      ]
    },
    {
      "id": "q4",
      "type": "relier",
      "question": "Final Mix Ch4 P1.",
      "pairs": [
        {
          "left": "No digas mentiras",
          "right": "Ne dis pas de mensonges"
        },
        {
          "left": "Opino que...",
          "right": "À mon avis..."
        },
        {
          "left": "Derechos",
          "right": "Droits"
        }
      ]
    },
    {
      "id": "q5",
      "type": "qcm",
      "enonce": "Felicidades ! ¿Listo para el Medio Ambiente (P2)?",
      "options": [
        "¡Sí!",
        "¡Adelante!",
        "¡Vamos!",
        "¡Vale!"
      ],
      "correctIndex": 1
    }
  ]
}
