{
  "id": "6-emc-ch3-q8",
  "titre": "Le débat démocratique",
  "questions": [
    {
      "type": "vrai_faux",
      "question": "Débattre, c'est échanger des idées et des arguments avec respect.",
      "answer": true
    },
    {
      "type": "qcm",
      "question": "Qu'est-ce qu'un argument ?",
      "options": [
        "Une insulte",
        "Une preuve ou un raisonnement qui sert à convaincre",
        "Un cri très fort",
        "Une blague"
      ],
      "answer": "Une preuve ou un raisonnement qui sert à convaincre"
    },
    {
      "type": "vrai_faux",
      "question": "Pendant un débat, on peut changer d'avis si les arguments des autres nous ont convaincus.",
      "answer": true
    },
    {
      "type": "qcm",
      "question": "L'écoute active pendant un débat consiste à :",
      "options": [
        "Préparer sa réponse sans écouter l'autre",
        "Essayer de comprendre réellement ce que dit l'autre",
        "Regarder par la fenêtre",
        "Faire du bruit avec ses doigts"
      ],
      "answer": "Essayer de comprendre réellement ce que dit l'autre"
    },
    {
      "type": "vrai_faux",
      "question": "Le débat est un outil essentiel de la démocratie.",
      "answer": true
    }
  ]
}
