{
  "id": "4-esp-ch1-q6",
  "titre": "Destinos Turísticos",
  "questions": [
    {
      "type": "vrai_faux",
      "question": "'España' está en el sur de Europa.",
      "answer": true
    },
    {
      "type": "qcm",
      "question": "Quel pays est célèbre pour le tango ?",
      "options": ["México", "Argentina", "España", "Perú"],
      "answer": "Argentina"
    },
    {
      "type": "vrai_faux",
      "question": "'La selva amazónica' se trouve en Afrique.",
      "answer": false
    },
    {
      "type": "qcm",
      "question": "Comment dit-on 'La jungle' ?",
      "options": ["El desierto", "La playa", "La selva", "El bosque"],
      "answer": "La selva"
    },
    {
      "type": "vrai_faux",
      "question": "'Las islas Baleares' (Mallorca, Ibiza) appartiennent à l'Espagne.",
      "answer": true
    }
  ]
}
