{
  "id": "6eme_SES_CH1_P1_QUIZ9",
  "classe": "6eme",
  "matiere": "SES",
  "chapitre": "chapitre_1",
  "partie": "partie_1",
  "titre": "Pourquoi échanger ?",
  "questions": [
    {
      "id": "q1",
      "question": "La 'division du travail' signifie :",
      "type": "QCM",
      "options": ["Diviser le temps de pause", "Répartir les tâches entre plusieurs personnes ou métiers", "Travailler seul sur tout", "Ne pas travailler"],
      "bonne_reponse": "Répartir les tâches entre plusieurs personnes ou métiers",
      "explication": "Chacun se spécialise pour être plus efficace."
    },
    {
      "id": "q2",
      "question": "Pourquoi personne ne fabrique tout tout seul ?",
      "type": "QCM",
      "options": ["Parce que c'est trop long et trop compliqué", "Parce que c'est interdit", "À cause du climat", "Parce qu'on est paresseux"],
      "bonne_reponse": "Parce que c'est trop long et trop compliqué",
      "explication": "L'échange permet de profiter du savoir-faire des autres."
    },
    {
      "id": "q3",
      "question": "Vrai ou Faux : L'échange permet d'avoir accès à plus de diversité de produits.",
      "type": "Vrai/Faux",
      "options": ["Vrai", "Faux"],
      "bonne_reponse": "Vrai",
      "explication": "On peut manger des bananes en France grâce aux échanges."
    },
    {
      "id": "q4",
      "question": "Qu'est-ce que l'autarcie ?",
      "type": "QCM",
      "options": ["Vivre uniquement de sa propre production sans échanges", "Acheter tout sur Internet", "Vendre tout à l'étranger", "Un type de bateau"],
      "bonne_reponse": "Vivre uniquement de sa propre production sans échanges",
      "explication": "C'est l'opposé de la société d'échange moderne."
    },
    {
      "id": "q5",
      "question": "Le commerce international est l'échange de biens entre :",
      "type": "QCM",
      "options": ["Voisins de palier", "Différents pays", "Deux magasins d'une même rue", "Les membres d'un ménage"],
      "bonne_reponse": "Différents pays",
      "explication": "C'est la base de la mondialisation."
    }
  ]
}
